{
    "adjacency_list": {
        "<SPACE>": [ "a" ],
        "a": [ "<SPACE>", "b" ],
        "b": [ "a", "c" ],
        "c": [ "b", "d" ],
        "d": [ "c", "e" ],
        "e": [ "d", "f" ],
        "f": [ "e", "g" ],
        "g": [ "f", "h" ],
        "h": [ "g", "i" ],
        "i": [ "h", "j" ],
        "j": [ "i", "k" ],
        "k": [ "j", "l" ],
        "l": [ "k", "m" ],
        "m": [ "l", "n" ],
        "n": [ "m", "o" ],
        "o": [ "n", "p" ],
        "p": [ "o", "q" ],
        "q": [ "p", "r" ],
        "r": [ "q", "s" ],
        "s": [ "r", "t" ],
        "t": [ "s", "u" ],
        "u": [ "t", "v" ],
        "v": [ "u", "w" ],
        "w": [ "v", "x" ],
        "x": [ "w", "y" ],
        "y": [ "x", "z" ],
        "z": [ "y", "<BACK>" ],
        "<BACK>": [ "z" ],
        "1": [ "2" ],
        "2": [ "1", "3" ],
        "3": [ "2", "4" ],
        "4": [ "3", "5" ],
        "5": [ "4", "6" ],
        "6": [ "5", "7" ],
        "7": [ "6", "8" ],
        "8": [ "7", "9" ],
        "9": [ "8", "0" ],
        "0": [ "9", "." ],
        ".": [ "0", "-" ],
        "-": [ ".", "_" ],
        "_": [ "-", "!" ],
        "!": [ "_", "@" ],
        "@": [ "!", "#" ],
        "#": [ "@", "$" ],
        "$": [ "#", "%" ],
        "%": [ "$", "^" ],
        "^": [ "%", "&" ],
        "&": [ "^", "*" ],
        "*": [ "9" ]
    },
    "shortcuts": {
        "<SPACE>": [ "1" ],
        "a": [ "1" ],
        "b": [ "1" ],
        "c": [ "1" ],
        "d": [ "2" ],
        "e": [ "3" ],
        "f": [ "4" ],
        "g": [ "5" ],
        "h": [ "6" ],
        "i": [ "7" ],
        "j": [ "8" ],
        "k": [ "9" ],
        "l": [ "0" ],
        "m": [ "." ],
        "n": [ "-" ],
        "o": [ "_" ],
        "p": [ "!" ],
        "q": [ "@" ],
        "r": [ "#" ],
        "s": [ "$" ],
        "t": [ "%" ],
        "u": [ "^" ],
        "v": [ "&" ],
        "w": [ "*" ],
        "x": [ "*" ],
        "y": [ "*" ],
        "z": [ "*" ],
        "<BACK>": ["*"],
        "1": [ "<SPACE>", "c" ],
        "2": [ "d" ],
        "3": [ "e" ],
        "4": [ "f" ],
        "5": [ "g" ],
        "6": [ "h" ],
        "7": [ "i" ],
        "8": [ "j" ],
        "9": [ "k" ],
        "0": [ "l" ],
        ".": [ "m" ],
        "-": [ "n" ],
        "_": [ "o" ],
        "!": [ "p" ],
        "@": [ "q" ],
        "#": [ "r" ],
        "$": [ "s" ],
        "%": [ "t" ],
        "^": [ "u" ],
        "&": [ "v" ],
        "*": [ "w", "<BACK>" ]
    },
    "wraparound": {},
    "unclickable": []
}
